{
  "item": [
    {
      "id": 360718080,
      "bvid": "BV1k94y1q7Ak",
      "cid": 1190585281,
      "goto": "av",
      "uri": "https://www.bilibili.com/video/BV1k94y1q7Ak",
      "pic": "http://i0.hdslb.com/bfs/archive/f6421db0d2b192ea6d91f94b17b4350a137c85b5.jpg",
      "title": "\u6211\u63a8\u7684\u7262\u5b50",
      "duration": 128,
      "pubdate": 1689041100,
      "owner": {
        "mid": 5260378,
        "name": "\u767d\u52fa\u554a\u8fbe",
        "face": "https://i1.hdslb.com/bfs/face/3c54240c8c92fd43fa0ee87f8bb42b39b2877055.jpg"
      },
      "stat": {
        "view": 2622542,
        "like": 420456,
        "danmaku": 3031,
        "vt": 0
      },
      "av_feature": null,
      "is_followed": 0,
      "rcmd_reason": null,
      "show_info": 0,
      "track_id": "",
      "pos": 0,
      "room_info": null,
      "ogv_info": null,
      "business_info": null,
      "is_stock": 0,
      "comic_detail_info": null,
      "game_detail_info": null,
      "enable_vt": 0
    },
    {
      "id": 230925679,
      "bvid": "BV1K8411Q7Dv",
      "cid": 1196771347,
      "goto": "av",
      "uri": "https://www.bilibili.com/video/BV1K8411Q7Dv",
      "pic": "http://i1.hdslb.com/bfs/archive/8975d96805e6ab8c635dfea9cdb5d7c974100230.jpg",
      "title": "\u795e\u79d8\u53d8\u6001\u6740\u4eba\u5272\u8089\uff0c\u5c45\u7136\u7ec4\u6210\u4e86\u4e00\u526f\u62fc\u56fe\uff1f\u762b\u75ea\u8b66\u5b98\u4ec5\u9760\u4e00\u6839\u624b\u6307\u7834\u6848\uff01\u60ac\u7591\u7ecf\u5178\u300a\u795e\u79d8\u62fc\u56fe\u300b",
      "duration": 2074,
      "pubdate": 1689413400,
      "owner": {
        "mid": 10119428,
        "name": "\u5c0f\u7247\u7247\u8bf4\u5927\u7247",
        "face": "https://i2.hdslb.com/bfs/face/949fd3f0b9fe23703c970d494edc41ae52ee32de.jpg"
      },
      "stat": {
        "view": 504233,
        "like": 33283,
        "danmaku": 1840,
        "vt": 0
      },
      "av_feature": null,
      "is_followed": 0,
      "rcmd_reason": null,
      "show_info": 0,
      "track_id": "",
      "pos": 0,
      "room_info": null,
      "ogv_info": null,
      "business_info": null,
      "is_stock": 0,
      "comic_detail_info": null,
      "game_detail_info": null,
      "enable_vt": 0
    },
    {
      "id": 445983185,
      "bvid": "BV19j411d7DS",
      "cid": 1196364523,
      "goto": "av",
      "uri": "https://www.bilibili.com/video/BV19j411d7DS",
      "pic": "http://i0.hdslb.com/bfs/archive/c9ea4d38fa489a00dc4ac692b9312f3d388a2f60.jpg",
      "title": "\u201c\u5929\u624d\u53ea\u662f\u89c1\u6211\u7684\u95e8\u69db\u3002\u201d",
      "duration": 219,
      "pubdate": 1689327090,
      "owner": {
        "mid": 239314942,
        "name": "\u4e03\u7af9ok",
        "face": "https://i1.hdslb.com/bfs/face/a345af2ad869aa27cd4b2f2ef6f8bda3f1dd0708.jpg"
      },
      "stat": {
        "view": 506058,
        "like": 19777,
        "danmaku": 562,
        "vt": 0
      },
      "av_feature": null,
      "is_followed": 0,
      "rcmd_reason": null,
      "show_info": 0,
      "track_id": "",
      "pos": 0,
      "room_info": null,
      "ogv_info": null,
      "business_info": null,
      "is_stock": 0,
      "comic_detail_info": null,
      "game_detail_info": null,
      "enable_vt": 0
    },
    {
      "id": 315837660,
      "bvid": "BV1pP411y7fV",
      "cid": 1195010537,
      "goto": "av",
      "uri": "https://www.bilibili.com/video/BV1pP411y7fV",
      "pic": "http://i1.hdslb.com/bfs/archive/ba2cdb49608193d11e8f74a5569e4793ae6be38e.jpg",
      "title": "\u9006\u5929\u5bd2\u662f\u4ec0\u4e48\u6897\u3010\u6897\u6307\u5357\u3011",
      "duration": 186,
      "pubdate": 1689328800,
      "owner": {
        "mid": 94510621,
        "name": "\u6897\u6307\u5357",
        "face": "https://i1.hdslb.com/bfs/face/9e649857c7c73452faabddcf2fbce1088f6e3ad5.jpg"
      },
      "stat": {
        "view": 1577260,
        "like": 115046,
        "danmaku": 1877,
        "vt": 0
      },
      "av_feature": null,
      "is_followed": 0,
      "rcmd_reason": null,
      "show_info": 0,
      "track_id": "",
      "pos": 0,
      "room_info": null,
      "ogv_info": null,
      "business_info": null,
      "is_stock": 0,
      "comic_detail_info": null,
      "game_detail_info": null,
      "enable_vt": 0
    },
    {
      "id": 315899433,
      "bvid": "BV13P411k7nd",
      "cid": 1197048270,
      "goto": "av",
      "uri": "https://www.bilibili.com/video/BV13P411k7nd",
      "pic": "http://i0.hdslb.com/bfs/archive/f20fd01f5d17de477de642253ca68c87b11c4f5d.jpg",
      "title": "\u592a\u9955\u992e\u4e86\u5427\uff1f\u5317\u4eac\u4e61\u6751\u91cc\u7684\u786c\u6838\u70e4\u8089\uff0c\u6765\u665a\u4e86\u5c31\u552e\u7f44",
      "duration": 817,
      "pubdate": 1689415200,
      "owner": {
        "mid": 39627524,
        "name": "\u98df\u8d2b\u9053",
        "face": "https://i2.hdslb.com/bfs/face/eef12b850c10b0d7a7929236abb08604955823c0.jpg"
      },
      "stat": {
        "view": 371761,
        "like": 23620,
        "danmaku": 2169,
        "vt": 0
      },
      "av_feature": null,
      "is_followed": 0,
      "rcmd_reason": null,
      "show_info": 0,
      "track_id": "",
      "pos": 0,
      "room_info": null,
      "ogv_info": null,
      "business_info": null,
      "is_stock": 0,
      "comic_detail_info": null,
      "game_detail_info": null,
      "enable_vt": 0
    },
    {
      "id": 700962894,
      "bvid": "BV1Fm4y1J7Y8",
      "cid": 1197298114,
      "goto": "av",
      "uri": "https://www.bilibili.com/video/BV1Fm4y1J7Y8",
      "pic": "http://i0.hdslb.com/bfs/archive/167d5231ca3a81d4460b0327fa8d7c583f08bffe.jpg",
      "title": "\u5927\u8111\u53d1\u80b2\u4e0d\u5b8c\u5168\uff0c\u5c0f\u8111\u5b8c\u5168\u4e0d\u53d1\u80b2",
      "duration": 445,
      "pubdate": 1689404744,
      "owner": {
        "mid": 19525533,
        "name": "KL_qiqi_",
        "face": "https://i0.hdslb.com/bfs/face/c5830e1e0142e04c96be9c87d3aef2e1b5d47581.jpg"
      },
      "stat": {
        "view": 541039,
        "like": 59925,
        "danmaku": 4724,
        "vt": 0
      },
      "av_feature": null,
      "is_followed": 0,
      "rcmd_reason": null,
      "show_info": 0,
      "track_id": "",
      "pos": 0,
      "room_info": null,
      "ogv_info": null,
      "business_info": null,
      "is_stock": 0,
      "comic_detail_info": null,
      "game_detail_info": null,
      "enable_vt": 0
    },
    {
      "id": 273397205,
      "bvid": "BV1rF41197gg",
      "cid": 1195288749,
      "goto": "av",
      "uri": "https://www.bilibili.com/video/BV1rF41197gg",
      "pic": "http://i0.hdslb.com/bfs/archive/0d749a5d78b72a6a8d93a5601ff101f62725db94.jpg",
      "title": "\u548c\u5b83\u73a9\u724c\u6839\u672c\u4e0d\u4f1a\u8d62\u554a",
      "duration": 166,
      "pubdate": 1689246591,
      "owner": {
        "mid": 320844275,
        "name": "\u997c\u4ebab",
        "face": "https://i2.hdslb.com/bfs/face/0c8f247216f5491166597fe4a57f1faf6135cca3.jpg"
      },
      "stat": {
        "view": 1472557,
        "like": 200435,
        "danmaku": 1299,
        "vt": 0
      },
      "av_feature": null,
      "is_followed": 0,
      "rcmd_reason": null,
      "show_info": 0,
      "track_id": "",
      "pos": 0,
      "room_info": null,
      "ogv_info": null,
      "business_info": null,
      "is_stock": 0,
      "comic_detail_info": null,
      "game_detail_info": null,
      "enable_vt": 0
    },
    {
      "id": 230997007,
      "bvid": "BV128411U7ch",
      "cid": 1196103135,
      "goto": "av",
      "uri": "https://www.bilibili.com/video/BV128411U7ch",
      "pic": "http://i0.hdslb.com/bfs/archive/13d3fb97c770c60865722140aca4f7f28b343f13.jpg",
      "title": "\u300a\u539f\u795e\u300b\uff1a\u201c\u5bfb\u627e\u539f\u7434\u5927\u4f6c\uff0c\u5728\u539f\u795e\u91cc\u70b9\u6b4c\u662f\u4ec0\u4e48\u6837\u7684\u4f53\u9a8c\u201d",
      "duration": 1243,
      "pubdate": 1689318793,
      "owner": {
        "mid": 400129819,
        "name": "\u6db2\u9570\u4e00\u5ca9\u738b\u5e1d\u53ea\u56e0",
        "face": "https://i1.hdslb.com/bfs/face/e193e06ed1a81721547ab3fb83d2cdcce2269032.jpg"
      },
      "stat": {
        "view": 398107,
        "like": 60010,
        "danmaku": 4811,
        "vt": 0
      },
      "av_feature": null,
      "is_followed": 0,
      "rcmd_reason": null,
      "show_info": 0,
      "track_id": "",
      "pos": 0,
      "room_info": null,
      "ogv_info": null,
      "business_info": null,
      "is_stock": 0,
      "comic_detail_info": null,
      "game_detail_info": null,
      "enable_vt": 0
    },
    {
      "id": 998499327,
      "bvid": "BV1Ax4y1Z7pG",
      "cid": 1196286840,
      "goto": "av",
      "uri": "https://www.bilibili.com/video/BV1Ax4y1Z7pG",
      "pic": "http://i1.hdslb.com/bfs/archive/c5b17415345878fa85342151b16737b75e728873.jpg",
      "title": "\u3010\u4e50\u9ad8\u5b9a\u683c\u52a8\u753b\u3011\u8fd9\u79cd\u62a5\u6069\u897f\u74dc\u6211\u4e0d\u5efa\u8bae\u5403\u3002",
      "duration": 93,
      "pubdate": 1689326956,
      "owner": {
        "mid": 628550554,
        "name": "\u554a\u545cQiu",
        "face": "https://i1.hdslb.com/bfs/face/04a616f19b53fbe4ebd0482b8e096aacf196bb9b.jpg"
      },
      "stat": {
        "view": 809052,
        "like": 63379,
        "danmaku": 427,
        "vt": 0
      },
      "av_feature": null,
      "is_followed": 0,
      "rcmd_reason": null,
      "show_info": 0,
      "track_id": "",
      "pos": 0,
      "room_info": null,
      "ogv_info": null,
      "business_info": null,
      "is_stock": 0,
      "comic_detail_info": null,
      "game_detail_info": null,
      "enable_vt": 0
    },
    {
      "id": 315913267,
      "bvid": "BV1KP411k7d1",
      "cid": 1197363373,
      "goto": "av",
      "uri": "https://www.bilibili.com/video/BV1KP411k7d1",
      "pic": "http://i0.hdslb.com/bfs/archive/d5c49918f154af800414cf69c97bec293644f50b.jpg",
      "title": "\u80d6\u9f99\u9001\u8d27\u4e0d\u5e72\u4e86\uff0c\u53c8\u5e94\u8058\u65b0\u5de5\u4f5c\uff0c\u4e2d\u5348\u5403\u4e2a\u6d77\u9c9c\u7116\u9762\uff0c\u52a8\u8d77\u6765",
      "duration": 302,
      "pubdate": 1689414300,
      "owner": {
        "mid": 649661652,
        "name": "\u80d6\u9f99\u7684\u5c0f\u751f\u6d3b",
        "face": "http://i0.hdslb.com/bfs/face/57ea78f573e9003880fc965932a1c93ad145cd59.jpg"
      },
      "stat": {
        "view": 574525,
        "like": 26934,
        "danmaku": 1423,
        "vt": 0
      },
      "av_feature": null,
      "is_followed": 0,
      "rcmd_reason": null,
      "show_info": 0,
      "track_id": "",
      "pos": 0,
      "room_info": null,
      "ogv_info": null,
      "business_info": null,
      "is_stock": 0,
      "comic_detail_info": null,
      "game_detail_info": null,
      "enable_vt": 0
    },
    {
      "id": 573392169,
      "bvid": "BV1jz4y177Yg",
      "cid": 1196993171,
      "goto": "av",
      "uri": "https://www.bilibili.com/video/BV1jz4y177Yg",
      "pic": "http://i2.hdslb.com/bfs/archive/4b5a9db2f08007c13797f9ec8c43ca014967af69.jpg",
      "title": "\u8d85\u8d8a\u4e09\u56fd\u6740\uff01\u5e74\u5ea6\u9006\u5929\u6e38\u620f\uff011W\u5143\u6311\u6218\u901a\u5173\u7687\u5ba4\u6218\u4e89#1\uff01",
      "duration": 693,
      "pubdate": 1689381830,
      "owner": {
        "mid": 450882837,
        "name": "\u4e00\u53ee\u5f53\u732b\u4e00",
        "face": "https://i0.hdslb.com/bfs/face/d1860f1dc772903037f0048c149b2b445e6bcc74.jpg"
      },
      "stat": {
        "view": 674673,
        "like": 50915,
        "danmaku": 3427,
        "vt": 0
      },
      "av_feature": null,
      "is_followed": 0,
      "rcmd_reason": null,
      "show_info": 0,
      "track_id": "",
      "pos": 0,
      "room_info": null,
      "ogv_info": null,
      "business_info": null,
      "is_stock": 0,
      "comic_detail_info": null,
      "game_detail_info": null,
      "enable_vt": 0
    },
    {
      "id": 273395343,
      "bvid": "BV1zF41197xQ",
      "cid": 1196916832,
      "goto": "av",
      "uri": "https://www.bilibili.com/video/BV1zF41197xQ",
      "pic": "http://i1.hdslb.com/bfs/archive/d5fae4dc54b425b73950630cf568f73a29d55f48.jpg",
      "title": "\u8fd9\u624d\u662f\u771f\u539f\u795e\uff01\u5927\u54e5\u7d2f\u4e86\u73a9\u4f1a\u513f\u539f\u795e\u548c\u5d293\u600e\u4e48\u4e86\uff1f",
      "duration": 138,
      "pubdate": 1689393600,
      "owner": {
        "mid": 629825579,
        "name": "\u7339\u6ce1\u996d233",
        "face": "https://i2.hdslb.com/bfs/face/5ff587e6a62d5f352cf804baa250c12a4a674b63.jpg"
      },
      "stat": {
        "view": 390907,
        "like": 39234,
        "danmaku": 1031,
        "vt": 0
      },
      "av_feature": null,
      "is_followed": 0,
      "rcmd_reason": null,
      "show_info": 0,
      "track_id": "",
      "pos": 0,
      "room_info": null,
      "ogv_info": null,
      "business_info": null,
      "is_stock": 0,
      "comic_detail_info": null,
      "game_detail_info": null,
      "enable_vt": 0
    },
    {
      "id": 998472312,
      "bvid": "BV19x4y1o7GJ",
      "cid": 1195890618,
      "goto": "av",
      "uri": "https://www.bilibili.com/video/BV19x4y1o7GJ",
      "pic": "http://i1.hdslb.com/bfs/archive/a85f102d96a54a20489cff164ca7c860a35bae64.jpg",
      "title": "\u7279\u53a8\u63a2\u5e97 |\u85cf\u5728\u5c45\u6c11\u697c\u7684\u5b9d\u85cf\u2014\u2014\u8700\u98ce\u60c5\u5bb6\u5e38\u83dc\uff01\u771f\u60f3\u628a\u4ed6\u7684\u505a\u83dc\u5e08\u5085\u7ed9\u6316\u8d70\uff01",
      "duration": 202,
      "pubdate": 1689393600,
      "owner": {
        "mid": 1462401621,
        "name": "\u7279\u53a8\u968b\u535e",
        "face": "https://i0.hdslb.com/bfs/face/0a28b42c7bfebc9ec6f8973646bcc2b54715c59c.jpg"
      },
      "stat": {
        "view": 482722,
        "like": 45546,
        "danmaku": 412,
        "vt": 0
      },
      "av_feature": null,
      "is_followed": 0,
      "rcmd_reason": null,
      "show_info": 0,
      "track_id": "",
      "pos": 0,
      "room_info": null,
      "ogv_info": null,
      "business_info": null,
      "is_stock": 0,
      "comic_detail_info": null,
      "game_detail_info": null,
      "enable_vt": 0
    },
    {
      "id": 530925438,
      "bvid": "BV1Cu41157hD",
      "cid": 1197269461,
      "goto": "av",
      "uri": "https://www.bilibili.com/video/BV1Cu41157hD",
      "pic": "http://i1.hdslb.com/bfs/archive/23cea467d5bbd379bc18b8cf67ab9a3f5e88c7d2.jpg",
      "title": "\u8d85\u9ad8\u60c5\u5546\u7559\u7ed9\u8bc4\u8bba\u533a",
      "duration": 29,
      "pubdate": 1689401426,
      "owner": {
        "mid": 480432696,
        "name": "\u95e8\u4e09\u77f3-",
        "face": "https://i0.hdslb.com/bfs/face/4daeef7b1a06722d226ed2f6c9fee61baed613a6.jpg"
      },
      "stat": {
        "view": 1122366,
        "like": 117207,
        "danmaku": 336,
        "vt": 0
      },
      "av_feature": null,
      "is_followed": 0,
      "rcmd_reason": null,
      "show_info": 0,
      "track_id": "",
      "pos": 0,
      "room_info": null,
      "ogv_info": null,
      "business_info": null,
      "is_stock": 0,
      "comic_detail_info": null,
      "game_detail_info": null,
      "enable_vt": 0
    },
    {
      "id": 315920990,
      "bvid": "BV1JP411k7ay",
      "cid": 1197592035,
      "goto": "av",
      "uri": "https://www.bilibili.com/video/BV1JP411k7ay",
      "pic": "http://i0.hdslb.com/bfs/archive/f39bb7ca1e77bf1a5c88a5d67921664d9586dd04.jpg",
      "title": "\u6e38\u620f\u515a\u5fc5\u770b\uff01\u4e2d\u7aefCPU\u5927\u4e71\u6597\uff0c\u8c01\u624d\u662f\u6027\u4ef7\u6bd4\u4e4b\u738b\uff1f13400F vs 12600KF vs 12400F vs 7600 vs 5600",
      "duration": 1373,
      "pubdate": 1689420997,
      "owner": {
        "mid": 151155077,
        "name": "\u5929\u624d\u8d75\u5fb7\u67f1",
        "face": "https://i2.hdslb.com/bfs/face/dbc8fd4bb583b58f339702e31072197f2b0e4fa7.jpg"
      },
      "stat": {
        "view": 228320,
        "like": 25898,
        "danmaku": 4259,
        "vt": 0
      },
      "av_feature": null,
      "is_followed": 0,
      "rcmd_reason": null,
      "show_info": 0,
      "track_id": "",
      "pos": 0,
      "room_info": null,
      "ogv_info": null,
      "business_info": null,
      "is_stock": 0,
      "comic_detail_info": null,
      "game_detail_info": null,
      "enable_vt": 0
    },
    {
      "id": 273445552,
      "bvid": "BV1NF411Q7vX",
      "cid": 1196627581,
      "goto": "av",
      "uri": "https://www.bilibili.com/video/BV1NF411Q7vX",
      "pic": "http://i0.hdslb.com/bfs/archive/ad631b6381f2a9eed30bf9147497fe3072a30f93.jpg",
      "title": "\u5f20\u5143\u82f1\u51fa\u9053\u81f3\u4eca68\u4e2a\u540d\u573a\u9762",
      "duration": 201,
      "pubdate": 1689341149,
      "owner": {
        "mid": 5024437,
        "name": "\u672a\u4e0e\u95fb",
        "face": "https://i1.hdslb.com/bfs/face/bc6eee813fa7d75f6c543df36142b6dbadf051e3.jpg"
      },
      "stat": {
        "view": 362870,
        "like": 32799,
        "danmaku": 586,
        "vt": 0
      },
      "av_feature": null,
      "is_followed": 0,
      "rcmd_reason": null,
      "show_info": 0,
      "track_id": "",
      "pos": 0,
      "room_info": null,
      "ogv_info": null,
      "business_info": null,
      "is_stock": 0,
      "comic_detail_info": null,
      "game_detail_info": null,
      "enable_vt": 0
    },
    {
      "id": 530892982,
      "bvid": "BV1Yu411575c",
      "cid": 1196414752,
      "goto": "av",
      "uri": "https://www.bilibili.com/video/BV1Yu411575c",
      "pic": "http://i1.hdslb.com/bfs/archive/ed5877b150fd08a2953383908eab1c853556e1fc.jpg",
      "title": "\u5143\u6b4c\uff1a\u50cf\u6211\u4eec\u8fd9\u79cd\u6570\u503c\u602a\u662f\u6253\u4e0d\u8fc7\u8fd9\u79cd\u624b\u6cd5\u82f1\u96c4\u7684",
      "duration": 148,
      "pubdate": 1689394339,
      "owner": {
        "mid": 178474181,
        "name": "\u5343\u4e1d\u6298\u7eb8\u9e3e--\u7433",
        "face": "https://i2.hdslb.com/bfs/face/027e0a791caa3677032b4b96187d49a41d965831.jpg"
      },
      "stat": {
        "view": 531740,
        "like": 44451,
        "danmaku": 456,
        "vt": 0
      },
      "av_feature": null,
      "is_followed": 0,
      "rcmd_reason": null,
      "show_info": 0,
      "track_id": "",
      "pos": 0,
      "room_info": null,
      "ogv_info": null,
      "business_info": null,
      "is_stock": 0,
      "comic_detail_info": null,
      "game_detail_info": null,
      "enable_vt": 0
    },
    {
      "id": 913294183,
      "bvid": "BV1XM4y1j75P",
      "cid": 1193069258,
      "goto": "av",
      "uri": "https://www.bilibili.com/video/BV1XM4y1j75P",
      "pic": "http://i2.hdslb.com/bfs/archive/8b689a56a1e59570b663ca2d70549c99f07c17cb.jpg",
      "title": "\u5728\u51b0\u51b7\u7684\u5bb6\u91cc\uff0c\u53ea\u6709\u6e38\u620f\u80fd\u6e29\u6696\u5b69\u5b50\u3002",
      "duration": 207,
      "pubdate": 1689079048,
      "owner": {
        "mid": 3461564856273771,
        "name": "\u738b\u7eaa\u743c\u4eb2\u5b50\u6559\u80b2",
        "face": "https://i0.hdslb.com/bfs/face/d2b7cc85771d2ea46aae84f43055b18dc8a28adb.jpg"
      },
      "stat": {
        "view": 1488328,
        "like": 245494,
        "danmaku": 3103,
        "vt": 0
      },
      "av_feature": null,
      "is_followed": 0,
      "rcmd_reason": null,
      "show_info": 0,
      "track_id": "",
      "pos": 0,
      "room_info": null,
      "ogv_info": null,
      "business_info": null,
      "is_stock": 0,
      "comic_detail_info": null,
      "game_detail_info": null,
      "enable_vt": 0
    },
    {
      "id": 315989925,
      "bvid": "BV1zP411k73F",
      "cid": 1197114318,
      "goto": "av",
      "uri": "https://www.bilibili.com/video/BV1zP411k73F",
      "pic": "http://i1.hdslb.com/bfs/archive/4765ad14158965e7814bb14726bbde9bd6b6797b.jpg",
      "title": "\u6551\u547d\uff01\u770b\u4e4b\u524d\u771f\u6ca1\u60f3\u5230\u4f1a\u8fd9\u4e48\u597d\u7b11\uff01",
      "duration": 318,
      "pubdate": 1689391178,
      "owner": {
        "mid": 5870268,
        "name": "\u4e09\u4ee3\u9e7f\u4eba",
        "face": "https://i0.hdslb.com/bfs/face/a915d1a1ff921cd418e74c5711c91b23e2a18c11.jpg"
      },
      "stat": {
        "view": 865276,
        "like": 65608,
        "danmaku": 1747,
        "vt": 0
      },
      "av_feature": null,
      "is_followed": 0,
      "rcmd_reason": null,
      "show_info": 0,
      "track_id": "",
      "pos": 0,
      "room_info": null,
      "ogv_info": null,
      "business_info": null,
      "is_stock": 0,
      "comic_detail_info": null,
      "game_detail_info": null,
      "enable_vt": 0
    },
    {
      "id": 955895478,
      "bvid": "BV12W4y1o7nk",
      "cid": 1197602714,
      "goto": "av",
      "uri": "https://www.bilibili.com/video/BV12W4y1o7nk",
      "pic": "http://i2.hdslb.com/bfs/archive/75ab94f3f374d8c3a4b4e7d0ae7d2a4e3b642fdf.jpg",
      "title": "(G)I-DLE\u3010\u4e2d\u5b57\u3011230715 \u7c73\u7426\u300a\u5954\u8dd1\u5c0f\u5ba2\u5385\u300b\u91c7\u8bbf",
      "duration": 1125,
      "pubdate": 1689421436,
      "owner": {
        "mid": 661188765,
        "name": "\u8b77\u5a03\u4f7f\u8005",
        "face": "https://i0.hdslb.com/bfs/face/03b29d2e097c1e202825af39e7681b3734bc1a26.jpg"
      },
      "stat": {
        "view": 275353,
        "like": 22481,
        "danmaku": 2717,
        "vt": 0
      },
      "av_feature": null,
      "is_followed": 0,
      "rcmd_reason": null,
      "show_info": 0,
      "track_id": "",
      "pos": 0,
      "room_info": null,
      "ogv_info": null,
      "business_info": null,
      "is_stock": 0,
      "comic_detail_info": null,
      "game_detail_info": null,
      "enable_vt": 0
    },
    {
      "id": 615910566,
      "bvid": "BV1Uh4y1j7r7",
      "cid": 1196691392,
      "goto": "av",
      "uri": "https://www.bilibili.com/video/BV1Uh4y1j7r7",
      "pic": "http://i1.hdslb.com/bfs/archive/a586cfec50fc6a45eea36219e9b2cb8c9b00381c.jpg",
      "title": "\u5973\u513f\u56fd\u8fb9\u5883\u6218\u4e89\uff1f\u8001\u541b\u53cd\u51fb\uff0c\u7389\u5e1d\u5982\u6765\u6b3a\u4eba\u592a\u751a\uff01",
      "duration": 1726,
      "pubdate": 1689382800,
      "owner": {
        "mid": 8096990,
        "name": "\u554a\u7ca5\u7ca5\u554a\u7ca5",
        "face": "https://i2.hdslb.com/bfs/face/79c1cf49166f6354d8814e93a4c8e1b55cfc03f2.jpg"
      },
      "stat": {
        "view": 620173,
        "like": 52341,
        "danmaku": 6959,
        "vt": 0
      },
      "av_feature": null,
      "is_followed": 0,
      "rcmd_reason": null,
      "show_info": 0,
      "track_id": "",
      "pos": 0,
      "room_info": null,
      "ogv_info": null,
      "business_info": null,
      "is_stock": 0,
      "comic_detail_info": null,
      "game_detail_info": null,
      "enable_vt": 0
    },
    {
      "id": 658494829,
      "bvid": "BV1eh4y1f7y1",
      "cid": 1196233675,
      "goto": "av",
      "uri": "https://www.bilibili.com/video/BV1eh4y1f7y1",
      "pic": "http://i1.hdslb.com/bfs/archive/75983d4f621cd621d90c4cf782749be0715e65bc.jpg",
      "title": "\u6ca1\u6709\u4eba\u6bd4\u6211\u4eec\u66f4\u4f1a\u5531\u8349\u4e1c",
      "duration": 206,
      "pubdate": 1689325485,
      "owner": {
        "mid": 2020642651,
        "name": "\u94c1\u76ae\u8f6f\u7cd6\u4e50\u961f",
        "face": "https://i1.hdslb.com/bfs/face/632811d636a3d0505a7cf5e88e9e10b00eb50f2b.jpg"
      },
      "stat": {
        "view": 289493,
        "like": 29821,
        "danmaku": 270,
        "vt": 0
      },
      "av_feature": null,
      "is_followed": 0,
      "rcmd_reason": null,
      "show_info": 0,
      "track_id": "",
      "pos": 0,
      "room_info": null,
      "ogv_info": null,
      "business_info": null,
      "is_stock": 0,
      "comic_detail_info": null,
      "game_detail_info": null,
      "enable_vt": 0
    },
    {
      "id": 360895107,
      "bvid": "BV1t94y1B7rn",
      "cid": 1196951407,
      "goto": "av",
      "uri": "https://www.bilibili.com/video/BV1t94y1B7rn",
      "pic": "http://i2.hdslb.com/bfs/archive/e9a252af96cffb49a0c9efbd520d025d5bfa4b60.jpg",
      "title": "\u70b9\u5916\u5356\u53d1\u73b0\u4e00\u4e2a\u5364\u9e45\u5934\u7adf1960\u5757\u94b1\uff1f\uff01\u5bf9\u6bd4\u770b\u770b\u8ddf\u666e\u901a\u5364\u9e45\u5934\u6709\u5565\u533a\u522b\uff01",
      "duration": 671,
      "pubdate": 1689408000,
      "owner": {
        "mid": 2920960,
        "name": "\u5927\u7965\u54e5\u6765\u4e86",
        "face": "https://i1.hdslb.com/bfs/face/2a752af02fa89ca9e296cc270e5c3e55b7dbf2e7.jpg"
      },
      "stat": {
        "view": 599275,
        "like": 30533,
        "danmaku": 3099,
        "vt": 0
      },
      "av_feature": null,
      "is_followed": 0,
      "rcmd_reason": null,
      "show_info": 0,
      "track_id": "",
      "pos": 0,
      "room_info": null,
      "ogv_info": null,
      "business_info": null,
      "is_stock": 0,
      "comic_detail_info": null,
      "game_detail_info": null,
      "enable_vt": 0
    },
    {
      "id": 615953807,
      "bvid": "BV1Ah4y1771M",
      "cid": 1196204637,
      "goto": "av",
      "uri": "https://www.bilibili.com/video/BV1Ah4y1771M",
      "pic": "http://i1.hdslb.com/bfs/archive/60f0bab333068c62ece7abebeda33bc7c9e9b0ea.jpg",
      "title": "\u4ece\u8303\u5fb7\u4e00\u5f6a\u5230\u6587\u827a\u5f71\u5e1d\uff0c\u8303\u4f1f\u8d70\u8fc7\u6f2b\u957f\u7684\u5b63\u8282 \u3010\u5bfb\u627e\u00b7\u8303\u4f1f\u3011",
      "duration": 1421,
      "pubdate": 1689332400,
      "owner": {
        "mid": 49246269,
        "name": "\u5927\u8c61\u653e\u6620\u5ba4",
        "face": "https://i0.hdslb.com/bfs/face/9d3229d6157767ebe386f37f33d075e348bea07d.jpg"
      },
      "stat": {
        "view": 792615,
        "like": 60287,
        "danmaku": 2026,
        "vt": 0
      },
      "av_feature": null,
      "is_followed": 0,
      "rcmd_reason": null,
      "show_info": 0,
      "track_id": "",
      "pos": 0,
      "room_info": null,
      "ogv_info": null,
      "business_info": null,
      "is_stock": 0,
      "comic_detail_info": null,
      "game_detail_info": null,
      "enable_vt": 0
    },
    {
      "id": 273327419,
      "bvid": "BV1JF41197a5",
      "cid": 1193104692,
      "goto": "av",
      "uri": "https://www.bilibili.com/video/BV1JF41197a5",
      "pic": "http://i1.hdslb.com/bfs/archive/2975a148c6b8e9de8d916e45f4952dca9f925617.jpg",
      "title": "\u201c \u6211 \u53ea \u8981 \u6211 \u7684 \u8774 \u8776 \u201d",
      "duration": 121,
      "pubdate": 1689067890,
      "owner": {
        "mid": 535622912,
        "name": "\u662f\u5e0c\u671b\u7684\u5e0cWish",
        "face": "https://i2.hdslb.com/bfs/face/6d0b9f586402085a604cc28d31e122d14d368f02.jpg"
      },
      "stat": {
        "view": 1955790,
        "like": 211156,
        "danmaku": 6290,
        "vt": 0
      },
      "av_feature": null,
      "is_followed": 0,
      "rcmd_reason": null,
      "show_info": 0,
      "track_id": "",
      "pos": 0,
      "room_info": null,
      "ogv_info": null,
      "business_info": null,
      "is_stock": 0,
      "comic_detail_info": null,
      "game_detail_info": null,
      "enable_vt": 0
    },
    {
      "id": 360980403,
      "bvid": "BV1H94y1i7KF",
      "cid": 1196369166,
      "goto": "av",
      "uri": "https://www.bilibili.com/video/BV1H94y1i7KF",
      "pic": "http://i0.hdslb.com/bfs/archive/3f0c59d4e4d59be4ecce9751dcd8c45b75f998db.jpg",
      "title": "\u300a\u5c11\u5973\u524d\u7ebf2\uff1a\u8ffd\u653e\u300b\u6574\u5907\u5ba4\u4eba\u5f62\u4e92\u52a8\u5c55\u793a\uff01",
      "duration": 121,
      "pubdate": 1689428100,
      "owner": {
        "mid": 697654195,
        "name": "\u5c11\u5973\u524d\u7ebf2-\u8ffd\u653e\u5236\u4f5c\u7ec4",
        "face": "https://i1.hdslb.com/bfs/face/b00fa47b1b1f6d929aca215c909928859993b5d4.jpg"
      },
      "stat": {
        "view": 238608,
        "like": 12768,
        "danmaku": 452,
        "vt": 0
      },
      "av_feature": null,
      "is_followed": 0,
      "rcmd_reason": null,
      "show_info": 0,
      "track_id": "",
      "pos": 0,
      "room_info": null,
      "ogv_info": null,
      "business_info": null,
      "is_stock": 0,
      "comic_detail_info": null,
      "game_detail_info": null,
      "enable_vt": 0
    },
    {
      "id": 998395776,
      "bvid": "BV1bx4y1o7SA",
      "cid": 1197654314,
      "goto": "av",
      "uri": "https://www.bilibili.com/video/BV1bx4y1o7SA",
      "pic": "http://i0.hdslb.com/bfs/archive/a25249884f66c0ec0236fa93d3cc226d5a3c8403.jpg",
      "title": "\u8fd9\u4e48\u4e2a\u62fd\u6cd5\u2026\u2026\u6307\u5b9a\u662f\u5e9f\u4e86",
      "duration": 199,
      "pubdate": 1689429182,
      "owner": {
        "mid": 3461565017754459,
        "name": "b\u963f\u725b\u5c0f\u5356\u90e8",
        "face": "https://i0.hdslb.com/bfs/face/4433f33fb898d721575855dc4335092e3cad7eaa.jpg"
      },
      "stat": {
        "view": 339897,
        "like": 26426,
        "danmaku": 1906,
        "vt": 0
      },
      "av_feature": null,
      "is_followed": 0,
      "rcmd_reason": null,
      "show_info": 0,
      "track_id": "",
      "pos": 0,
      "room_info": null,
      "ogv_info": null,
      "business_info": null,
      "is_stock": 0,
      "comic_detail_info": null,
      "game_detail_info": null,
      "enable_vt": 0
    },
    {
      "id": 403382794,
      "bvid": "BV19V411T7CH",
      "cid": 1195978076,
      "goto": "av",
      "uri": "https://www.bilibili.com/video/BV19V411T7CH",
      "pic": "http://i1.hdslb.com/bfs/archive/ccd2213df684a8d9297b1e7dc3c36c09ae372ff9.jpg",
      "title": "\u5927\u54e5\u5f00\u4e2a\u673a\u7532\u600e\u4e48\u4e86\uff1f\uff1f",
      "duration": 146,
      "pubdate": 1689384600,
      "owner": {
        "mid": 144709395,
        "name": "\u5c0f\u5357QAQ",
        "face": "https://i0.hdslb.com/bfs/face/b5e069df48e7736019970d4ca983503f11d31708.jpg"
      },
      "stat": {
        "view": 524278,
        "like": 40657,
        "danmaku": 478,
        "vt": 0
      },
      "av_feature": null,
      "is_followed": 0,
      "rcmd_reason": null,
      "show_info": 0,
      "track_id": "",
      "pos": 0,
      "room_info": null,
      "ogv_info": null,
      "business_info": null,
      "is_stock": 0,
      "comic_detail_info": null,
      "game_detail_info": null,
      "enable_vt": 0
    },
    {
      "id": 743445690,
      "bvid": "BV16k4y1V76W",
      "cid": 1197502378,
      "goto": "av",
      "uri": "https://www.bilibili.com/video/BV16k4y1V76W",
      "pic": "http://i0.hdslb.com/bfs/archive/15ba32560525a749a778d2f3d9cefdb33b72f305.jpg",
      "title": "\u7a7f\u8d8a\u7684\u5c34\u5c2c\u77ac\u95f4",
      "duration": 233,
      "pubdate": 1689415214,
      "owner": {
        "mid": 1548805549,
        "name": "\u751c\u871c\u8001\u5f20",
        "face": "https://i1.hdslb.com/bfs/face/8e1b3812f8c0c20b5d2ef1bb3a332077b5c951bc.jpg"
      },
      "stat": {
        "view": 490240,
        "like": 51115,
        "danmaku": 898,
        "vt": 0
      },
      "av_feature": null,
      "is_followed": 0,
      "rcmd_reason": null,
      "show_info": 0,
      "track_id": "",
      "pos": 0,
      "room_info": null,
      "ogv_info": null,
      "business_info": null,
      "is_stock": 0,
      "comic_detail_info": null,
      "game_detail_info": null,
      "enable_vt": 0
    },
    {
      "id": 998389649,
      "bvid": "BV1Bx4y1o7os",
      "cid": 1197156188,
      "goto": "av",
      "uri": "https://www.bilibili.com/video/BV1Bx4y1o7os",
      "pic": "http://i1.hdslb.com/bfs/archive/6bb717fbabc005703a0dd155429919758747e7ef.jpg",
      "title": "\u88ab\u903c\u75af\u7684\u6253\u5de5\u4eba\u68b5\u9ad8\uff01\u80cc\u540e\u66b4\u9732\u4e86\u7236\u6bcd\u4ee4\u4eba\u7a92\u606f\u7684\u7cbe\u795e\u66b4\u529b\uff01",
      "duration": 642,
      "pubdate": 1689394005,
      "owner": {
        "mid": 192090,
        "name": "\u5c0f\u900f\u660e\u660eTM",
        "face": "https://i0.hdslb.com/bfs/face/dac77542be0f716bc0837a08d17868ba5a651836.jpg"
      },
      "stat": {
        "view": 321727,
        "like": 42041,
        "danmaku": 2232,
        "vt": 0
      },
      "av_feature": null,
      "is_followed": 0,
      "rcmd_reason": null,
      "show_info": 0,
      "track_id": "",
      "pos": 0,
      "room_info": null,
      "ogv_info": null,
      "business_info": null,
      "is_stock": 0,
      "comic_detail_info": null,
      "game_detail_info": null,
      "enable_vt": 0
    }
  ],
  "side_bar_column": null,
  "business_card": null,
  "floor_info": null,
  "user_feature": null,
  "abtest": {
    "group": "a"
  },
  "preload_expose_pct": 0,
  "preload_floor_expose_pct": 0,
  "mid": 0
}
